dhondtxai/__init__.py
dhondtxai/dhondt_xai.py
dhondtxai/plot_parliament.py
dhondtxai-0.6.2.3.dist-info/METADATA
dhondtxai-0.6.2.3.dist-info/WHEEL
dhondtxai-0.6.2.3.dist-info/top_level.txt
dhondtxai-0.6.2.3.dist-info/RECORD
